fauxy/__init__.py
fauxy/app.py
fauxy/library.py
fauxy/record.py
fauxy-0.0.2.dist-info/METADATA
fauxy-0.0.2.dist-info/WHEEL
fauxy-0.0.2.dist-info/RECORD
