Metadata-Version: 2.1
Name: fauxy
Version: 0.0.2
Summary: Faux responses from proxying
Home-page: https://github.com/groves/fauxy
License: Apache-2.0
Author: Charlie Groves
Author-email: c@sevorg.org
Requires-Python: >=3.10,<4.0
Classifier: License :: OSI Approved :: Apache Software License
Classifier: Programming Language :: Python :: 3
Classifier: Programming Language :: Python :: 3.10
Classifier: Programming Language :: Python :: 3.11
Requires-Dist: httpx (>=0.24.0,<0.25.0)
Requires-Dist: starlette (>=0.26.1,<0.27.0)
Requires-Dist: uvicorn (>=0.22.0,<0.23.0)
Project-URL: Repository, https://github.com/groves/fauxy
